q2_dbbact/__init__.py
q2_dbbact/methods.py
q2_dbbact/plugin_setup.py
q2_dbbact/utils.py
q2_dbbact/visualizations.py
q2_dbbact-1.5.0.dist-info/LICENSE
q2_dbbact-1.5.0.dist-info/METADATA
q2_dbbact-1.5.0.dist-info/WHEEL
q2_dbbact-1.5.0.dist-info/entry_points.txt
q2_dbbact-1.5.0.dist-info/top_level.txt
q2_dbbact-1.5.0.dist-info/RECORD
