Metadata-Version: 2.1
Name: q2-dbbact
Version: 1.5.0
Summary: A qiime2 (https://qiime2.org/) plugin for dbBact (http://dbbact.org) annotations of microbiome experiments
Home-page: http://dbbact.org
Author: dbBact team
Author-email: info@dbbact.org
License: BSD
Keywords: microbiome qiime2 dbbact database analysis bioinformatics
Classifier: Development Status :: 4 - Beta
Classifier: License :: OSI Approved :: BSD License
Classifier: Environment :: Plugins
Classifier: Topic :: Software Development :: Libraries :: Application Frameworks
Classifier: Topic :: Scientific/Engineering
Classifier: Topic :: Scientific/Engineering :: Bio-Informatics
Classifier: Programming Language :: Python
Classifier: Programming Language :: Python :: 3
Classifier: Programming Language :: Python :: 3.6
Classifier: Programming Language :: Python :: 3.7
Classifier: Programming Language :: Python :: 3.8
Classifier: Operating System :: Unix
Classifier: Operating System :: POSIX
Classifier: Operating System :: MacOS :: MacOS X
Classifier: Operating System :: Microsoft :: Windows
Requires-Python: >=3.6
License-File: LICENSE
Requires-Dist: wordcloud
Requires-Dist: calour
Requires-Dist: dbbact-calour
